leakage_buster/__init__.py
leakage_buster/api.py
leakage_buster/cli.py
leakage_buster/core/checks.py
leakage_buster/core/cv_policy.py
leakage_buster/core/export.py
leakage_buster/core/fix_apply.py
leakage_buster/core/fix_plan.py
leakage_buster/core/loader.py
leakage_buster/core/parallel.py
leakage_buster/core/report.py
leakage_buster/core/simulator.py
leakage_buster/templates/report.html.j2
leakage_buster-1.0.2.dist-info/licenses/LICENSE
leakage_buster-1.0.2.dist-info/METADATA
leakage_buster-1.0.2.dist-info/WHEEL
leakage_buster-1.0.2.dist-info/entry_points.txt
leakage_buster-1.0.2.dist-info/top_level.txt
leakage_buster-1.0.2.dist-info/RECORD
