Metadata-Version: 2.4
Name: leakage-buster
Version: 1.0.2
Summary: Data leakage detection and audit tool for machine learning
Home-page: https://github.com/li147852xu/leakage-buster
Author: Leakage Buster Team
Author-email: Leakage Buster Team <team@leakage-buster.dev>
Maintainer-email: Leakage Buster Team <team@leakage-buster.dev>
License: MIT
Project-URL: Homepage, https://github.com/li147852xu/leakage-buster
Project-URL: Documentation, https://leakage-buster.readthedocs.io
Project-URL: Repository, https://github.com/li147852xu/leakage-buster.git
Project-URL: Issues, https://github.com/li147852xu/leakage-buster/issues
Project-URL: Changelog, https://github.com/li147852xu/leakage-buster/blob/main/CHANGELOG.md
Keywords: machine-learning,data-leakage,audit,validation,cross-validation,time-series,feature-engineering
Classifier: Development Status :: 5 - Production/Stable
Classifier: Intended Audience :: Developers
Classifier: Intended Audience :: Science/Research
Classifier: License :: OSI Approved :: MIT License
Classifier: Operating System :: OS Independent
Classifier: Programming Language :: Python :: 3
Classifier: Programming Language :: Python :: 3.9
Classifier: Programming Language :: Python :: 3.10
Classifier: Programming Language :: Python :: 3.11
Classifier: Programming Language :: Python :: 3.12
Classifier: Topic :: Scientific/Engineering :: Artificial Intelligence
Classifier: Topic :: Software Development :: Libraries :: Python Modules
Classifier: Topic :: Software Development :: Quality Assurance
Classifier: Topic :: Software Development :: Testing
Requires-Python: >=3.9
License-File: LICENSE
Requires-Dist: pandas<3.0,>=2.0
Requires-Dist: numpy<2.0,>=1.23
Requires-Dist: scikit-learn<2.0,>=1.2
Requires-Dist: jinja2<4.0,>=3.1
Requires-Dist: pyyaml>=6.0
Requires-Dist: pydantic>=2.0
Requires-Dist: psutil>=5.9
Provides-Extra: pdf
Requires-Dist: weasyprint>=61; extra == "pdf"
Provides-Extra: polars
Requires-Dist: polars>=0.20; extra == "polars"
Provides-Extra: dev
Requires-Dist: pytest>=7; extra == "dev"
Requires-Dist: pytest-cov>=4; extra == "dev"
Requires-Dist: ruff>=0.5; extra == "dev"
Requires-Dist: mypy>=1.9; python_version >= "3.10" and extra == "dev"
Provides-Extra: docs
Requires-Dist: sphinx>=5.0; extra == "docs"
Requires-Dist: sphinx-rtd-theme>=1.0; extra == "docs"
Requires-Dist: myst-parser>=1.0; extra == "docs"
Provides-Extra: perf
Requires-Dist: polars>=0.20.0; extra == "perf"
Requires-Dist: joblib>=1.3; extra == "perf"
Dynamic: author
Dynamic: home-page
Dynamic: license-file
Dynamic: requires-python
